replacement_lru.v
module replacement_lru(
    input clk,
    input rst,
    input access_update,
    input [1:0] set_idx,
    input accessed_way,
    output victim_way
);

    reg recent_way [0:3];
    integer i;

    initial begin
        for (i = 0; i < 4; i = i + 1)
            recent_way[i] = 0;
    end

    assign victim_way = ~recent_way[set_idx];

    always @(posedge clk or posedge rst) begin
        if (rst) begin
            for (i = 0; i < 4; i = i + 1)
                recent_way[i] <= 0;
        end
        else if (access_update) begin
            recent_way[set_idx] <= accessed_way;
        end
    end

endmodule

repplacement_fifo.v
module replacement_fifo(
    input clk,
    input rst,
    input update,
    input [1:0] set_idx,
    output victim_way
);

    reg fifo_ptr [0:3];
    integer i;

    initial begin
        for (i = 0; i < 4; i = i + 1)
            fifo_ptr[i] = 0;
    end

    assign victim_way = fifo_ptr[set_idx];

    always @(posedge clk or posedge rst) begin
        if (rst) begin
            for (i = 0; i < 4; i = i + 1)
                fifo_ptr[i] <= 0;
        end
        else if (update) begin
            fifo_ptr[set_idx] <= ~fifo_ptr[set_idx];
        end
    end

endmodule

main_memory.v
module main_memory(
    input clk,
    input we,
    input [7:0] addr,
    input [15:0] write_data,
    output [15:0] read_data
);

    reg [15:0] mem [0:255];
    integer i;

    initial begin
        for (i = 0; i < 256; i = i + 1)
            mem[i] = i * 3 + 1;
    end

    assign read_data = mem[addr];

    always @(posedge clk) begin
        if (we)
            mem[addr] <= write_data;
    end

endmodule

cache_memory.v
module cache_memory(
    input clk,
    input we,
    input [1:0] set_idx,
    input way_sel,

    input [15:0] write_data,
    input [5:0]  write_tag,
    input write_valid,
    input write_dirty,

    output reg [15:0] read_data0,
    output reg [15:0] read_data1,
    output reg [5:0] read_tag0,
    output reg [5:0] read_tag1,
    output reg read_valid0,
    output reg read_valid1,
    output reg read_dirty0,
    output reg read_dirty1
);

    reg [15:0] data_mem0 [0:3];
    reg [15:0] data_mem1 [0:3];

    reg [5:0] tag_mem0 [0:3];
    reg [5:0] tag_mem1 [0:3];

    reg valid0 [0:3];
    reg valid1 [0:3];

    reg dirty0 [0:3];
    reg dirty1 [0:3];

    integer i;

    initial begin
        for (i = 0; i < 4; i = i + 1) begin
            data_mem0[i] = 0;
            data_mem1[i] = 0;
            tag_mem0[i] = 0;
            tag_mem1[i] = 0;
            valid0[i] = 0;
            valid1[i] = 0;
            dirty0[i] = 0;
            dirty1[i] = 0;
        end
    end

    always @(*) begin
        read_data0 = data_mem0[set_idx];
        read_data1 = data_mem1[set_idx];
        read_tag0 = tag_mem0[set_idx];
        read_tag1 = tag_mem1[set_idx];
        read_valid0 = valid0[set_idx];
        read_valid1 = valid1[set_idx];
        read_dirty0 = dirty0[set_idx];
        read_dirty1 = dirty1[set_idx];
    end

    always @(posedge clk) begin
        if (we) begin
            if (way_sel == 0) begin
                data_mem0[set_idx] <= write_data;
                tag_mem0[set_idx] <= write_tag;
                valid0[set_idx] <= write_valid;
                dirty0[set_idx] <= write_dirty;
            end
            else begin
                data_mem1[set_idx] <= write_data;
                tag_mem1[set_idx] <= write_tag;
                valid1[set_idx] <= write_valid;
                dirty1[set_idx] <= write_dirty;
            end
        end
    end

endmodule

address_decoder.v
module address_decoder(
    input  [7:0] address,
    output [5:0] tag,
    output [1:0] index
);

    assign index = address[1:0];
    assign tag   = address[7:2];

endmodule

cache_controller.v
module cache_controller(
    input clk,
    input rst,

    input req_valid,
    input read_en,
    input write_en,
    input policy_select,   // 0 = FIFO, 1 = LRU

    input  [7:0]  address,
    input  [15:0] write_data,

    output reg [15:0] read_data,
    output reg hit,
    output reg [31:0] hit_count,
    output reg [31:0] miss_count
);

    wire [5:0] tag;
    wire [1:0] index;

    wire [15:0] cdata0, cdata1;
    wire [5:0] ctag0, ctag1;
    wire cvalid0, cvalid1;
    wire cdirty0, cdirty1;

    reg cache_we;
    reg cache_way_sel;
    reg [15:0] cache_write_data;
    reg [5:0] cache_write_tag;
    reg cache_write_valid;
    reg cache_write_dirty;

    reg mem_we;
    wire [15:0] mem_read_data;

    reg fifo_update;
    reg lru_update;
    reg lru_accessed_way;

    wire fifo_victim;
    wire lru_victim;

    wire way0_hit;
    wire way1_hit;

    address_decoder u_decoder(
        .address(address),
        .tag(tag),
        .index(index)
    );

    cache_memory u_cache_memory(
        .clk(clk),
        .we(cache_we),
        .set_idx(index),
        .way_sel(cache_way_sel),
        .write_data(cache_write_data),
        .write_tag(cache_write_tag),
        .write_valid(cache_write_valid),
        .write_dirty(cache_write_dirty),
        .read_data0(cdata0),
        .read_data1(cdata1),
        .read_tag0(ctag0),
        .read_tag1(ctag1),
        .read_valid0(cvalid0),
        .read_valid1(cvalid1),
        .read_dirty0(cdirty0),
        .read_dirty1(cdirty1)
    );

    main_memory u_main_memory(
        .clk(clk),
        .we(mem_we),
        .addr(address),
        .write_data(write_data),
        .read_data(mem_read_data)
    );

    replacement_fifo u_fifo(
        .clk(clk),
        .rst(rst),
        .update(fifo_update),
        .set_idx(index),
        .victim_way(fifo_victim)
    );

    replacement_lru u_lru(
        .clk(clk),
        .rst(rst),
        .access_update(lru_update),
        .set_idx(index),
        .accessed_way(lru_accessed_way),
        .victim_way(lru_victim)
    );

    assign way0_hit = cvalid0 && (ctag0 == tag);
    assign way1_hit = cvalid1 && (ctag1 == tag);

    always @(posedge clk or posedge rst) begin
        if (rst) begin
            read_data         <= 0;
            hit               <= 0;
            hit_count         <= 0;
            miss_count        <= 0;

            cache_we <= 0;
            cache_way_sel <= 0;
            cache_write_data <= 0;
            cache_write_tag <= 0;
            cache_write_valid <= 0;
            cache_write_dirty <= 0;

            mem_we <= 0;
            fifo_update <= 0;
            lru_update <= 0;
            lru_accessed_way <= 0;
        end
        else begin
            cache_we <= 0;
            mem_we <= 0;
            fifo_update <= 0;
            lru_update <= 0;
            hit <= 0;

            if (req_valid && (read_en || write_en)) begin

                if (way0_hit || way1_hit) begin
                    hit <= 1;
                    hit_count <= hit_count + 1;

                    if (read_en) begin
                        if (way0_hit)
                            read_data <= cdata0;
                        else
                            read_data <= cdata1;
                    end

                    if (write_en) begin
                        cache_we <= 1;
                        cache_way_sel <= way0_hit ? 0 : 1;
                        cache_write_data <= write_data;
                        cache_write_tag <= tag;
                        cache_write_valid <= 1;
                        cache_write_dirty <= 0;

                        mem_we <= 1;   // write-through
                    end

                    lru_update       <= 1;
                    lru_accessed_way <= way0_hit ? 0 : 1;
                end

                else begin
                    hit <= 0;
                    miss_count <= miss_count + 1;

                    cache_we <= 1;
                    cache_write_tag <= tag;
                    cache_write_valid <= 1;
                    cache_write_dirty <= 0;

                    if (!cvalid0)
                        cache_way_sel <= 0;
                    else if (!cvalid1)
                        cache_way_sel <= 1;
                    else
                        cache_way_sel <= (policy_select) ? lru_victim : fifo_victim;

                    if (read_en) begin
                        cache_write_data <= mem_read_data;
                        read_data <= mem_read_data;
                    end

                    if (write_en) begin
                        cache_write_data <= write_data;
                        mem_we <= 1;
                    end

                    if (cvalid0 && cvalid1)
                        fifo_update <= 1;

                    lru_update <= 1;

                    if (!cvalid0)
                        lru_accessed_way <= 0;
                    else if (!cvalid1)
                        lru_accessed_way <= 1;
                    else
                        lru_accessed_way <= (policy_select) ? lru_victim : fifo_victim;
                end
            end
        end
    end

endmodule

cache_top.v
module cache_top(
    input clk,
    input rst,

    input req_valid,
    input read_en,
    input write_en,
    input policy_select,

    input  [7:0]  address,
    input  [15:0] write_data,

    output [15:0] read_data,
    output hit,
    output [31:0] hit_count,
    output [31:0] miss_count
);

    cache_controller u_controller(
        .clk(clk),
        .rst(rst),
        .req_valid(req_valid),
        .read_en(read_en),
        .write_en(write_en),
        .policy_select(policy_select),
        .address(address),
        .write_data(write_data),
        .read_data(read_data),
        .hit(hit),
        .hit_count(hit_count),
        .miss_count(miss_count)
    );

endmodule

tb_cache.v
`timescale 1ns/1ps

module tb_cache;

    reg clk;
    reg rst;
    reg req_valid;
    reg read_en;
    reg write_en;
    reg policy_select;   // 0 = FIFO, 1 = LRU
    reg [7:0] address;
    reg [15:0] write_data;

    wire [15:0] read_data;
    wire hit;
    wire [31:0] hit_count;
    wire [31:0] miss_count;

    integer total_accesses;
    real hit_rate;
    real miss_rate;
    integer i;

    cache_top dut(
        .clk(clk),
        .rst(rst),
        .req_valid(req_valid),
        .read_en(read_en),
        .write_en(write_en),
        .policy_select(policy_select),
        .address(address),
        .write_data(write_data),
        .read_data(read_data),
        .hit(hit),
        .hit_count(hit_count),
        .miss_count(miss_count)
    );

    always #5 clk = ~clk;

    task clear_cache_state;
        begin
            for (i = 0; i < 4; i = i + 1) begin
                // Clear cache memory contents
                dut.u_controller.u_cache_memory.data_mem0[i] = 16'd0;
                dut.u_controller.u_cache_memory.data_mem1[i] = 16'd0;
                dut.u_controller.u_cache_memory.tag_mem0[i]  = 6'd0;
                dut.u_controller.u_cache_memory.tag_mem1[i]  = 6'd0;
                dut.u_controller.u_cache_memory.valid0[i]    = 1'b0;
                dut.u_controller.u_cache_memory.valid1[i]    = 1'b0;
                dut.u_controller.u_cache_memory.dirty0[i]    = 1'b0;
                dut.u_controller.u_cache_memory.dirty1[i]    = 1'b0;

                // Clear FIFO and LRU tracking
                dut.u_controller.u_fifo.fifo_ptr[i]   = 1'b0;
                dut.u_controller.u_lru.recent_way[i]  = 1'b0;
            end
        end
    endtask

    task do_read;
        input [7:0] addr;
        begin
            @(negedge clk);
            req_valid  = 1;
            read_en    = 1;
            write_en   = 0;
            address    = addr;
            write_data = 0;

            @(posedge clk);
            #1;
            total_accesses = total_accesses + 1;
            $display("Time=%0t Policy=%s READ  Addr=%0d Hit=%0d Data=%0d Hits=%0d Misses=%0d",
                     $time, policy_select ? "LRU " : "FIFO", addr, hit, read_data, hit_count, miss_count);

            @(negedge clk);
            req_valid = 0;
            read_en   = 0;
            write_en  = 0;
        end
    endtask

    task do_write;
        input [7:0] addr;
        input [15:0] data;
        begin
            @(negedge clk);
            req_valid  = 1;
            read_en    = 0;
            write_en   = 1;
            address    = addr;
            write_data = data;

            @(posedge clk);
            #1;
            total_accesses = total_accesses + 1;
            $display("Time=%0t Policy=%s WRITE Addr=%0d WData=%0d Hit=%0d Hits=%0d Misses=%0d",
                     $time, policy_select ? "LRU " : "FIFO", addr, data, hit, hit_count, miss_count);

            @(negedge clk);
            req_valid = 0;
            read_en   = 0;
            write_en  = 0;
        end
    endtask

    task reset_dut;
        begin
            rst = 1;
            req_valid = 0;
            read_en = 0;
            write_en = 0;
            address = 0;
            write_data = 0;
            total_accesses = 0;

            clear_cache_state();

            #12;
            rst = 0;
        end
    endtask

    task print_summary;
        input [8*40:1] testname;
        begin
            hit_rate  = (total_accesses > 0) ? (hit_count * 100.0) / total_accesses : 0.0;
            miss_rate = (total_accesses > 0) ? (miss_count * 100.0) / total_accesses : 0.0;

            $display("------------------------------------------------------------");
            $display("Test Case : %0s", testname);
            $display("Policy    : %0s", policy_select ? "LRU" : "FIFO");
            $display("Accesses  : %0d", total_accesses);
            $display("Hits      : %0d", hit_count);
            $display("Misses    : %0d", miss_count);
            $display("Hit Rate  : %0.2f %%", hit_rate);
            $display("Miss Rate : %0.2f %%", miss_rate);
            $display("------------------------------------------------------------");
        end
    endtask

    initial begin
        $dumpfile("cache.vcd");
        $dumpvars(0, tb_cache);
    end

    initial begin
        clk = 0;

        // =========================================================
        // TEST CASE 1 : Conflict Pattern
        // Sequence: 0, 4, 0, 8, 0
        // =========================================================
        policy_select = 0;
        reset_dut();
        do_read(8'd0);
        do_read(8'd4);
        do_read(8'd0);
        do_read(8'd8);
        do_read(8'd0);
        print_summary("TC1 Conflict Pattern");

        policy_select = 1;
        reset_dut();
        do_read(8'd0);
        do_read(8'd4);
        do_read(8'd0);
        do_read(8'd8);
        do_read(8'd0);
        print_summary("TC1 Conflict Pattern");

        // =========================================================
        // TEST CASE 2 : High Locality
        // Sequence: 1, 1, 1, 1, 1
        // =========================================================
        policy_select = 0;
        reset_dut();
        do_read(8'd1);
        do_read(8'd1);
        do_read(8'd1);
        do_read(8'd1);
        do_read(8'd1);
        print_summary("TC2 High Locality");

        policy_select = 1;
        reset_dut();
        do_read(8'd1);
        do_read(8'd1);
        do_read(8'd1);
        do_read(8'd1);
        do_read(8'd1);
        print_summary("TC2 High Locality");

        // =========================================================
        // TEST CASE 3 : Streaming Pattern
        // Sequence: 0, 1, 2, 3, 4, 5
        // =========================================================
        policy_select = 0;
        reset_dut();
        do_read(8'd0);
        do_read(8'd1);
        do_read(8'd2);
        do_read(8'd3);
        do_read(8'd4);
        do_read(8'd5);
        print_summary("TC3 Streaming Pattern");

        policy_select = 1;
        reset_dut();
        do_read(8'd0);
        do_read(8'd1);
        do_read(8'd2);
        do_read(8'd3);
        do_read(8'd4);
        do_read(8'd5);
        print_summary("TC3 Streaming Pattern");

        // =========================================================
        // TEST CASE 4 : Mixed Reuse
        // Sequence: 0, 4, 8, 4, 0, 8, 4
        // =========================================================
        policy_select = 0;
        reset_dut();
        do_read(8'd0);
        do_read(8'd4);
        do_read(8'd8);
        do_read(8'd4);
        do_read(8'd0);
        do_read(8'd8);
        do_read(8'd4);
        print_summary("TC4 Mixed Reuse");

        policy_select = 1;
        reset_dut();
        do_read(8'd0);
        do_read(8'd4);
        do_read(8'd8);
        do_read(8'd4);
        do_read(8'd0);
        do_read(8'd8);
        do_read(8'd4);
        print_summary("TC4 Mixed Reuse");

        // =========================================================
        // TEST CASE 5 : Write Test
        // Sequence: write 12, read 12, write 12, read 12
        // =========================================================
        policy_select = 0;
        reset_dut();
        do_write(8'd12, 16'd555);
        do_read(8'd12);
        do_write(8'd12, 16'd777);
        do_read(8'd12);
        print_summary("TC5 Write Test");

        policy_select = 1;
        reset_dut();
        do_write(8'd12, 16'd555);
        do_read(8'd12);
        do_write(8'd12, 16'd777);
        do_read(8'd12);
        print_summary("TC5 Write Test");

        #20;
        $finish;
    end

endmodule

cache.vcd
$date
	Thu Apr 23 17:01:33 2026
$end
$version
	Icarus Verilog
$end
$timescale
	1ps
$end
$scope module tb_cache $end
$var wire 16 ! read_data [15:0] $end
$var wire 32 " miss_count [31:0] $end
$var wire 32 # hit_count [31:0] $end
$var wire 1 $ hit $end
$var reg 8 % address [7:0] $end
$var reg 1 & clk $end
$var reg 1 ' policy_select $end
$var reg 1 ( read_en $end
$var reg 1 ) req_valid $end
$var reg 1 * rst $end
$var reg 16 + write_data [15:0] $end
$var reg 1 , write_en $end
$var real 1 - hit_rate $end
$var integer 32 . i [31:0] $end
$var real 1 / miss_rate $end
$var integer 32 0 total_accesses [31:0] $end
$scope module dut $end
$var wire 8 1 address [7:0] $end
$var wire 1 & clk $end
$var wire 1 ' policy_select $end
$var wire 1 ( read_en $end
$var wire 1 ) req_valid $end
$var wire 1 * rst $end
$var wire 16 2 write_data [15:0] $end
$var wire 1 , write_en $end
$var wire 16 3 read_data [15:0] $end
$var wire 32 4 miss_count [31:0] $end
$var wire 32 5 hit_count [31:0] $end
$var wire 1 $ hit $end
$scope module u_controller $end
$var wire 8 6 address [7:0] $end
$var wire 1 & clk $end
$var wire 1 ' policy_select $end
$var wire 1 ( read_en $end
$var wire 1 ) req_valid $end
$var wire 1 * rst $end
$var wire 1 7 way0_hit $end
$var wire 1 8 way1_hit $end
$var wire 16 9 write_data [15:0] $end
$var wire 1 , write_en $end
$var wire 6 : tag [5:0] $end
$var wire 16 ; mem_read_data [15:0] $end
$var wire 1 < lru_victim $end
$var wire 2 = index [1:0] $end
$var wire 1 > fifo_victim $end
$var wire 1 ? cvalid1 $end
$var wire 1 @ cvalid0 $end
$var wire 6 A ctag1 [5:0] $end
$var wire 6 B ctag0 [5:0] $end
$var wire 1 C cdirty1 $end
$var wire 1 D cdirty0 $end
$var wire 16 E cdata1 [15:0] $end
$var wire 16 F cdata0 [15:0] $end
$var reg 1 G cache_way_sel $end
$var reg 1 H cache_we $end
$var reg 16 I cache_write_data [15:0] $end
$var reg 1 J cache_write_dirty $end
$var reg 6 K cache_write_tag [5:0] $end
$var reg 1 L cache_write_valid $end
$var reg 1 M fifo_update $end
$var reg 1 $ hit $end
$var reg 32 N hit_count [31:0] $end
$var reg 1 O lru_accessed_way $end
$var reg 1 P lru_update $end
$var reg 1 Q mem_we $end
$var reg 32 R miss_count [31:0] $end
$var reg 16 S read_data [15:0] $end
$scope module u_cache_memory $end
$var wire 1 & clk $end
$var wire 1 G way_sel $end
$var wire 1 H we $end
$var wire 16 T write_data [15:0] $end
$var wire 1 J write_dirty $end
$var wire 6 U write_tag [5:0] $end
$var wire 1 L write_valid $end
$var wire 2 V set_idx [1:0] $end
$var reg 16 W read_data0 [15:0] $end
$var reg 16 X read_data1 [15:0] $end
$var reg 1 D read_dirty0 $end
$var reg 1 C read_dirty1 $end
$var reg 6 Y read_tag0 [5:0] $end
$var reg 6 Z read_tag1 [5:0] $end
$var reg 1 @ read_valid0 $end
$var reg 1 ? read_valid1 $end
$var integer 32 [ i [31:0] $end
$upscope $end
$scope module u_decoder $end
$var wire 8 \ address [7:0] $end
$var wire 6 ] tag [5:0] $end
$var wire 2 ^ index [1:0] $end
$upscope $end
$scope module u_fifo $end
$var wire 1 & clk $end
$var wire 1 * rst $end
$var wire 2 _ set_idx [1:0] $end
$var wire 1 M update $end
$var wire 1 > victim_way $end
$var integer 32 ` i [31:0] $end
$upscope $end
$scope module u_lru $end
$var wire 1 P access_update $end
$var wire 1 O accessed_way $end
$var wire 1 & clk $end
$var wire 1 * rst $end
$var wire 2 a set_idx [1:0] $end
$var wire 1 < victim_way $end
$var integer 32 b i [31:0] $end
$upscope $end
$scope module u_main_memory $end
$var wire 8 c addr [7:0] $end
$var wire 1 & clk $end
$var wire 16 d read_data [15:0] $end
$var wire 1 Q we $end
$var wire 16 e write_data [15:0] $end
$var integer 32 f i [31:0] $end
$upscope $end
$upscope $end
$upscope $end
$scope task clear_cache_state $end
$upscope $end
$scope task do_read $end
$var reg 8 g addr [7:0] $end
$upscope $end
$scope task do_write $end
$var reg 8 h addr [7:0] $end
$var reg 16 i data [15:0] $end
$upscope $end
$scope task print_summary $end
$var reg 320 j testname [320:1] $end
$upscope $end
$scope task reset_dut $end
$upscope $end
$upscope $end
$enddefinitions $end
$comment Show the parameter values. $end
$dumpall
$end
#0
$dumpvars
bx j
bx i
bx h
bx g
b100000000 f
b0 e
b1 d
b0 c
b100 b
b0 a
b100 `
b0 _
b0 ^
b0 ]
b0 \
b100 [
b0 Z
b0 Y
b0 X
b0 W
b0 V
b0 U
b0 T
b0 S
b0 R
0Q
0P
0O
b0 N
0M
0L
b0 K
0J
b0 I
0H
0G
b0 F
b0 E
0D
0C
b0 B
b0 A
0@
0?
0>
b0 =
1<
b1 ;
b0 :
b0 9
08
07
b0 6
b0 5
b0 4
b0 3
b0 2
b0 1
b0 0
r0 /
b100 .
r0 -
0,
b0 +
1*
0)
0(
0'
0&
b0 %
0$
b0 #
b0 "
b0 !
$end
#5000
b100 b
b100 `
1&
#10000
0&
#12000
b0 g
0*
#15000
1&
#20000
1(
1)
0&
#25000
1P
b1 !
b1 3
b1 S
b1 I
b1 T
1L
1H
b1 "
b1 4
b1 R
1&
#26000
b1 0
#30000
b100 g
0(
0)
0&
#35000
17
1@
b1 F
b1 W
0P
0H
1&
#40000
07
b1 :
b1 ]
b1101 ;
b1101 d
b100 %
b100 1
b100 6
b100 \
b100 c
1(
1)
0&
#45000
1O
1P
b1101 !
b1101 3
b1101 S
b1101 I
b1101 T
1G
b1 K
b1 U
1H
b10 "
b10 4
b10 R
1&
#46000
b10 0
#50000
b0 g
0(
0)
0&
#55000
18
0<
1?
b1 A
b1 Z
b1101 E
b1101 X
0P
0H
1&
#60000
08
17
b0 :
b0 ]
b1 ;
b1 d
b0 %
b0 1
b0 6
b0 \
b0 c
1(
1)
0&
#65000
0O
1P
b1 !
b1 3
b1 S
b1 #
b1 5
b1 N
1$
1&
#66000
b11 0
#70000
b1000 g
0(
0)
0&
#75000
1<
0$
0P
1&
#80000
07
b10 :
b10 ]
b11001 ;
b11001 d
b1000 %
b1000 1
b1000 6
b1000 \
b1000 c
1(
1)
0&
#85000
1P
1M
b11001 !
b11001 3
b11001 S
b11001 I
b11001 T
0G
b10 K
b10 U
1H
b11 "
b11 4
b11 R
1&
#86000
b100 0
#90000
b0 g
0(
0)
0&
#95000
17
b10 B
b10 Y
b11001 F
b11001 W
1>
0P
0M
0H
1&
#100000
07
b0 :
b0 ]
b1 ;
b1 d
b0 %
b0 1
b0 6
b0 \
b0 c
1(
1)
0&
#105000
1O
1P
1M
b1 !
b1 3
b1 S
b1 I
b1 T
1G
b0 K
b0 U
1H
b100 "
b100 4
b100 R
1&
#106000
b101 0
#110000
0O
0P
0M
0L
b0 I
b0 T
0G
0H
b0 "
b0 4
b0 R
b0 #
b0 5
b0 N
b0 !
b0 3
b0 S
0?
0@
b0 A
b0 Z
b0 B
b0 Y
b0 E
b0 X
b0 F
b0 W
b100 `
b100 b
0>
b100 .
b0 0
1*
1'
r80 /
r20 -
b101010001000011001100010010000001000011011011110110111001100110011011000110100101100011011101000010000001010000011000010111010001110100011001010111001001101110 j
0(
0)
0&
#115000
b100 b
b100 `
1&
#120000
0&
#122000
0*
#125000
1&
#130000
1(
1)
0&
#135000
1P
b1 !
b1 3
b1 S
b1 I
b1 T
1L
1H
b1 "
b1 4
b1 R
1&
#136000
b1 0
#140000
b100 g
0(
0)
0&
#145000
17
1@
b1 F
b1 W
0P
0H
1&
#150000
07
b1 :
b1 ]
b1101 ;
b1101 d
b100 %
b100 1
b100 6
b100 \
b100 c
1(
1)
0&
#155000
1O
1P
b1101 !
b1101 3
b1101 S
b1101 I
b1101 T
1G
b1 K
b1 U
1H
b10 "
b10 4
b10 R
1&
#156000
b10 0
#160000
b0 g
0(
0)
0&
#165000
18
0<
1?
b1 A
b1 Z
b1101 E
b1101 X
0P
0H
1&
#170000
08
17
b0 :
b0 ]
b1 ;
b1 d
b0 %
b0 1
b0 6
b0 \
b0 c
1(
1)
0&
#175000
0O
1P
b1 !
b1 3
b1 S
b1 #
b1 5
b1 N
1$
1&
#176000
b11 0
#180000
b1000 g
0(
0)
0&
#185000
1<
0$
0P
1&
#190000
07
b10 :
b10 ]
b11001 ;
b11001 d
b1000 %
b1000 1
b1000 6
b1000 \
b1000 c
1(
1)
0&
#195000
1O
1P
1M
b11001 !
b11001 3
b11001 S
b11001 I
b11001 T
b10 K
b10 U
1H
b11 "
b11 4
b11 R
1&
#196000
b100 0
#200000
b0 g
0(
0)
0&
#205000
18
0<
b10 A
b10 Z
b11001 E
b11001 X
1>
0P
0M
0H
1&
#210000
08
17
b0 :
b0 ]
b1 ;
b1 d
b0 %
b0 1
b0 6
b0 \
b0 c
1(
1)
0&
#215000
0O
1P
b1 !
b1 3
b1 S
b10 #
b10 5
b10 N
1$
1&
#216000
b101 0
#220000
0P
0L
b0 K
b0 U
b0 I
b0 T
0G
b0 "
b0 4
b0 R
b0 #
b0 5
b0 N
0$
b0 !
b0 3
b0 S
07
1<
0?
0@
b0 A
b0 Z
b0 E
b0 X
b0 F
b0 W
b100 `
b100 b
0>
b100 .
b0 0
1*
0'
r60 /
r40 -
0(
0)
0&
#225000
b100 b
b100 `
1&
#230000
0&
#232000
b1 g
0*
#235000
1&
#240000
b1 =
b1 V
b1 ^
b1 _
b1 a
b100 ;
b100 d
b1 %
b1 1
b1 6
b1 \
b1 c
1(
1)
0&
#245000
1P
b100 !
b100 3
b100 S
b100 I
b100 T
1L
1H
b1 "
b1 4
b1 R
1&
#246000
b1 0
#250000
0(
0)
0&
#255000
17
1@
b100 F
b100 W
0P
0H
1&
#260000
1(
1)
0&
#265000
1P
b1 #
b1 5
b1 N
1$
1&
#266000
b10 0
#270000
0(
0)
0&
#275000
0$
0P
1&
#280000
1(
1)
0&
#285000
1P
b10 #
b10 5
b10 N
1$
1&
#286000
b11 0
#290000
0(
0)
0&
#295000
0$
0P
1&
#300000
1(
1)
0&
#305000
1P
b11 #
b11 5
b11 N
1$
1&
#306000
b100 0
#310000
0(
0)
0&
#315000
0$
0P
1&
#320000
1(
1)
0&
#325000
1P
b100 #
b100 5
b100 N
1$
1&
#326000
b101 0
#330000
0P
0L
b0 I
b0 T
b0 "
b0 4
b0 R
b0 #
b0 5
b0 N
0$
b0 !
b0 3
b0 S
07
0@
b0 F
b0 W
b0 =
b0 V
b0 ^
b0 _
b0 a
b100 `
b100 b
b100 .
b0 0
b1 ;
b1 d
b0 %
b0 1
b0 6
b0 \
b0 c
1*
1'
r20 /
r80 -
b101010001000011001100100010000001001000011010010110011101101000001000000100110001101111011000110110000101101100011010010111010001111001 j
0(
0)
0&
#335000
b100 b
b100 `
1&
#340000
0&
#342000
0*
#345000
1&
#350000
b1 =
b1 V
b1 ^
b1 _
b1 a
b100 ;
b100 d
b1 %
b1 1
b1 6
b1 \
b1 c
1(
1)
0&
#355000
1P
b100 !
b100 3
b100 S
b100 I
b100 T
1L
1H
b1 "
b1 4
b1 R
1&
#356000
b1 0
#360000
0(
0)
0&
#365000
17
1@
b100 F
b100 W
0P
0H
1&
#370000
1(
1)
0&
#375000
1P
b1 #
b1 5
b1 N
1$
1&
#376000
b10 0
#380000
0(
0)
0&
#385000
0$
0P
1&
#390000
1(
1)
0&
#395000
1P
b10 #
b10 5
b10 N
1$
1&
#396000
b11 0
#400000
0(
0)
0&
#405000
0$
0P
1&
#410000
1(
1)
0&
#415000
1P
b11 #
b11 5
b11 N
1$
1&
#416000
b100 0
#420000
0(
0)
0&
#425000
0$
0P
1&
#430000
1(
1)
0&
#435000
1P
b100 #
b100 5
b100 N
1$
1&
#436000
b101 0
#440000
0P
0L
b0 I
b0 T
b0 "
b0 4
b0 R
b0 #
b0 5
b0 N
0$
b0 !
b0 3
b0 S
07
0@
b0 F
b0 W
b0 =
b0 V
b0 ^
b0 _
b0 a
b100 `
b100 b
b100 .
b0 0
b1 ;
b1 d
b0 %
b0 1
b0 6
b0 \
b0 c
1*
0'
0(
0)
0&
#445000
b100 b
b100 `
1&
#450000
0&
#452000
b0 g
0*
#455000
1&
#460000
1(
1)
0&
#465000
1P
b1 !
b1 3
b1 S
b1 I
b1 T
1L
1H
b1 "
b1 4
b1 R
1&
#466000
b1 0
#470000
b1 g
0(
0)
0&
#475000
17
1@
b1 F
b1 W
0P
0H
1&
#480000
07
0@
b0 F
b0 W
b1 =
b1 V
b1 ^
b1 _
b1 a
b100 ;
b100 d
b1 %
b1 1
b1 6
b1 \
b1 c
1(
1)
0&
#485000
1P
b100 !
b100 3
b100 S
b100 I
b100 T
1H
b10 "
b10 4
b10 R
1&
#486000
b10 0
#490000
b10 g
0(
0)
0&
#495000
17
1@
b100 F
b100 W
0P
0H
1&
#500000
07
0@
b0 F
b0 W
b10 =
b10 V
b10 ^
b10 _
b10 a
b111 ;
b111 d
b10 %
b10 1
b10 6
b10 \
b10 c
1(
1)
0&
#505000
1P
b111 !
b111 3
b111 S
b111 I
b111 T
1H
b11 "
b11 4
b11 R
1&
#506000
b11 0
#510000
b11 g
0(
0)
0&
#515000
17
1@
b111 F
b111 W
0P
0H
1&
#520000
07
0@
b0 F
b0 W
b11 =
b11 V
b11 ^
b11 _
b11 a
b1010 ;
b1010 d
b11 %
b11 1
b11 6
b11 \
b11 c
1(
1)
0&
#525000
1P
b1010 !
b1010 3
b1010 S
b1010 I
b1010 T
1H
b100 "
b100 4
b100 R
1&
#526000
b100 0
#530000
b100 g
0(
0)
0&
#535000
17
1@
b1010 F
b1010 W
0P
0H
1&
#540000
b1 F
b1 W
07
b0 =
b0 V
b0 ^
b0 _
b0 a
b1 :
b1 ]
b1101 ;
b1101 d
b100 %
b100 1
b100 6
b100 \
b100 c
1(
1)
0&
#545000
1O
1P
b1101 !
b1101 3
b1101 S
b1101 I
b1101 T
1G
b1 K
b1 U
1H
b101 "
b101 4
b101 R
1&
#546000
b101 0
#550000
b101 g
0(
0)
0&
#555000
18
0<
1?
b1 A
b1 Z
b1101 E
b1101 X
0P
0H
1&
#560000
08
1<
0?
b0 A
b0 Z
b0 E
b0 X
b100 F
b100 W
b1 =
b1 V
b1 ^
b1 _
b1 a
b10000 ;
b10000 d
b101 %
b101 1
b101 6
b101 \
b101 c
1(
1)
0&
#565000
1P
b10000 !
b10000 3
b10000 S
b10000 I
b10000 T
1H
b110 "
b110 4
b110 R
1&
#566000
b110 0
#570000
0O
0P
0L
b0 K
b0 U
b0 I
b0 T
0G
0H
b0 "
b0 4
b0 R
b0 !
b0 3
b0 S
0@
b0 F
b0 W
b0 =
b0 V
b0 ^
b0 _
b0 a
b0 :
b0 ]
b100 `
b100 b
b100 .
b0 0
b1 ;
b1 d
b0 %
b0 1
b0 6
b0 \
b0 c
1*
1'
r100 /
r0 -
b10101000100001100110011001000000101001101110100011100100110010101100001011011010110100101101110011001110010000001010000011000010111010001110100011001010111001001101110 j
0(
0)
0&
#575000
b100 b
b100 `
1&
#580000
0&
#582000
b0 g
0*
#585000
1&
#590000
1(
1)
0&
#595000
1P
b1 !
b1 3
b1 S
b1 I
b1 T
1L
1H
b1 "
b1 4
b1 R
1&
#596000
b1 0
#600000
b1 g
0(
0)
0&
#605000
17
1@
b1 F
b1 W
0P
0H
1&
#610000
07
0@
b0 F
b0 W
b1 =
b1 V
b1 ^
b1 _
b1 a
b100 ;
b100 d
b1 %
b1 1
b1 6
b1 \
b1 c
1(
1)
0&
#615000
1P
b100 !
b100 3
b100 S
b100 I
b100 T
1H
b10 "
b10 4
b10 R
1&
#616000
b10 0
#620000
b10 g
0(
0)
0&
#625000
17
1@
b100 F
b100 W
0P
0H
1&
#630000
07
0@
b0 F
b0 W
b10 =
b10 V
b10 ^
b10 _
b10 a
b111 ;
b111 d
b10 %
b10 1
b10 6
b10 \
b10 c
1(
1)
0&
